README.txt
setup.py
nspawn_tools/__init__.py
nspawn_tools/machine.py
nspawn_tools.egg-info/PKG-INFO
nspawn_tools.egg-info/SOURCES.txt
nspawn_tools.egg-info/dependency_links.txt
nspawn_tools.egg-info/entry_points.txt
nspawn_tools.egg-info/requires.txt
nspawn_tools.egg-info/top_level.txt
nspawn_tools/cli/__init__.py
nspawn_tools/cli/enter.py
nspawn_tools/cli/stop.py